mathics_pygments/__init__.py
mathics_pygments/builtins.py
mathics_pygments/lexer.py
mathics_pygments/style.py
mathics_pygments/version.py
mathics_pygments/data/mma-tables.json
mathics_pygments-1.0.3.dist-info/LICENSE
mathics_pygments-1.0.3.dist-info/METADATA
mathics_pygments-1.0.3.dist-info/WHEEL
mathics_pygments-1.0.3.dist-info/entry_points.txt
mathics_pygments-1.0.3.dist-info/top_level.txt
mathics_pygments-1.0.3.dist-info/RECORD
