Metadata-Version: 2.1
Name: mathics_pygments
Version: 1.0.3
Summary: Mathematica/Wolfram Language Lexer for Pygments
Home-page: http://github.com/Mathics3/mathics-pygments/
Author: Rocky Bernstein
Author-email: rb@dustyfeet.com
License: MIT
Keywords: syntax highlighting mathematica
Platform: any
Classifier: Development Status :: 4 - Beta
Classifier: Intended Audience :: End Users/Desktop
Classifier: License :: OSI Approved :: MIT License
Classifier: Operating System :: OS Independent
Classifier: Programming Language :: Python
Classifier: Programming Language :: Python :: 3.6
Classifier: Programming Language :: Python :: 3.7
Classifier: Programming Language :: Python :: 3.8
Classifier: Programming Language :: Python :: 3.9
Classifier: Programming Language :: Python :: 3.10
Classifier: Programming Language :: Python :: 3.11
Classifier: Programming Language :: Python :: 3.12
Classifier: Topic :: Text Processing
Classifier: Topic :: Utilities
License-File: LICENSE
Requires-Dist: Pygments >=2.9.0
Requires-Dist: Mathics-Scanner >=1.3.0
